graphene_django_optimizer/__init__.py
graphene_django_optimizer/field.py
graphene_django_optimizer/hints.py
graphene_django_optimizer/query.py
graphene_django_optimizer/resolver.py
graphene_django_optimizer/types.py
graphene_django_optimizer/utils.py
graphene_django_optimizer-0.10.0.dist-info/LICENSE
graphene_django_optimizer-0.10.0.dist-info/METADATA
graphene_django_optimizer-0.10.0.dist-info/WHEEL
graphene_django_optimizer-0.10.0.dist-info/top_level.txt
graphene_django_optimizer-0.10.0.dist-info/RECORD
