Metadata-Version: 2.1
Name: graphene-django-optimizer
Version: 0.10.0
Summary: Optimize database access inside graphene queries.
Home-page: https://github.com/tfoxy/graphene-django-optimizer
Author: Tomás Fox
Author-email: tomas.c.fox@gmail.com
License: MIT
Keywords: graphene django optimizer optimize graphql query prefetch select related
Classifier: Development Status :: 4 - Beta
Classifier: Environment :: Web Environment
Classifier: Intended Audience :: Developers
Classifier: License :: OSI Approved :: MIT License
Classifier: Operating System :: OS Independent
Classifier: Programming Language :: Python
Classifier: Programming Language :: Python :: 3
Classifier: Programming Language :: Python :: 3.6
Classifier: Programming Language :: Python :: 3.7
Classifier: Programming Language :: Python :: 3.8
Classifier: Framework :: Django
Classifier: Framework :: Django :: 2.2
Classifier: Framework :: Django :: 3.1
License-File: LICENSE
